abvd/ABVD.py
abvd/__init__.py
abvd/download.py
abvd/download_fast.py
abvd/tools.py
abvdget-2.0.dist-info/METADATA
abvdget-2.0.dist-info/WHEEL
abvdget-2.0.dist-info/entry_points.txt
abvdget-2.0.dist-info/licenses/LICENSE
abvdget-2.0.dist-info/RECORD
