Metadata-Version: 2.4
Name: abvdget
Version: 2.0
Summary: Download data from the Austronesian Basic Vocabulary Database
Author-email: "Simon J. Greenhill" <simon@simon.net.nz>
License-Expression: MIT AND (Apache-2.0 OR BSD-2-Clause)
License-File: LICENSE
Requires-Python: >=3.13
Requires-Dist: httpx>=0.28.1
